{
  "repoName": "home-theater-projector-resource-map",
  "shortDescription": "Resource map for Better Buy Lab projector, home theater, screen size, dark-room setup, and TV vs projector buying decisions.",
  "description": "Resource map for Better Buy Lab projector, home theater, screen size, dark-room setup, and TV vs projector buying decisions.",
  "homepage": "https://www.betterbuylab.com/home-theater",
  "topics": [
    "betterbuylab",
    "buying-guides",
    "product-research",
    "projectors",
    "home-theater",
    "dark-room",
    "screen-size",
    "buyer-fit",
    "consumer-tech",
    "entertainment"
  ],
  "visibility": "public",
  "pinnedRecommendation": false,
  "profilePurpose": "Projector and home theater constraint maps with TV sibling overlap.",
  "primaryWebsitePages": [
    "/home-theater",
    "/home-theater/best-projectors"
  ],
  "complianceNotes": "Room-fit framing; no throw-distance guarantees without page support."
}
